[
	{
		"__typename": "QuestionLightNode",
		"acRate": 0.43105238319962247,
		"difficulty": "EASY",
		"freqBar": 0,
		"paidOnly": true,
		"status": "NOT_STARTED",
		"frontendQuestionId": "1056",
		"isFavor": false,
		"solutionNum": 95,
		"title": "Confusing Number",
		"titleCn": "易混淆数",
		"titleSlug": "confusing-number"
	},
	{
		"__typename": "QuestionLightNode",
		"acRate": 0.501123595505618,
		"difficulty": "MEDIUM",
		"freqBar": 0,
		"paidOnly": true,
		"status": "NOT_STARTED",
		"frontendQuestionId": "1057",
		"isFavor": false,
		"solutionNum": 54,
		"title": "Campus Bikes",
		"titleCn": "校园自行车分配",
		"titleSlug": "campus-bikes"
	},
	{
		"__typename": "QuestionLightNode",
		"acRate": 0.3646694214876033,
		"difficulty": "MEDIUM",
		"freqBar": 0,
		"paidOnly": true,
		"status": "NOT_STARTED",
		"frontendQuestionId": "1058",
		"isFavor": false,
		"solutionNum": 47,
		"title": "Minimize Rounding Error to Meet Target",
		"titleCn": "最小化舍入误差以满足目标",
		"titleSlug": "minimize-rounding-error-to-meet-target"
	},
	{
		"__typename": "QuestionLightNode",
		"acRate": 0.36482525366403606,
		"difficulty": "MEDIUM",
		"freqBar": 0,
		"paidOnly": true,
		"status": "NOT_STARTED",
		"frontendQuestionId": "1059",
		"isFavor": false,
		"solutionNum": 46,
		"title": "All Paths from Source Lead to Destination",
		"titleCn": "从始点到终点的所有路径",
		"titleSlug": "all-paths-from-source-lead-to-destination"
	},
	{
		"__typename": "QuestionLightNode",
		"acRate": 0.5394231289571947,
		"difficulty": "MEDIUM",
		"freqBar": 0,
		"paidOnly": true,
		"status": "NOT_STARTED",
		"frontendQuestionId": "1060",
		"isFavor": false,
		"solutionNum": 140,
		"title": "Missing Element in Sorted Array",
		"titleCn": "有序数组中的缺失元素",
		"titleSlug": "missing-element-in-sorted-array"
	},
	{
		"__typename": "QuestionLightNode",
		"acRate": 0.6274987810823989,
		"difficulty": "MEDIUM",
		"freqBar": 0,
		"paidOnly": true,
		"status": "NOT_STARTED",
		"frontendQuestionId": "1061",
		"isFavor": false,
		"solutionNum": 90,
		"title": "Lexicographically Smallest Equivalent String",
		"titleCn": "按字典序排列最小的等效字符串",
		"titleSlug": "lexicographically-smallest-equivalent-string"
	},
	{
		"__typename": "QuestionLightNode",
		"acRate": 0.5612870789341378,
		"difficulty": "MEDIUM",
		"freqBar": 0,
		"paidOnly": true,
		"status": "NOT_STARTED",
		"frontendQuestionId": "1062",
		"isFavor": false,
		"solutionNum": 81,
		"title": "Longest Repeating Substring",
		"titleCn": "最长重复子串",
		"titleSlug": "longest-repeating-substring"
	},
	{
		"__typename": "QuestionLightNode",
		"acRate": 0.7325488098422038,
		"difficulty": "HARD",
		"freqBar": 0,
		"paidOnly": true,
		"status": "NOT_STARTED",
		"frontendQuestionId": "1063",
		"isFavor": false,
		"solutionNum": 58,
		"title": "Number of Valid Subarrays",
		"titleCn": "有效子数组的数目",
		"titleSlug": "number-of-valid-subarrays"
	},
	{
		"__typename": "QuestionLightNode",
		"acRate": 0.8455944283941784,
		"difficulty": "EASY",
		"freqBar": 0,
		"paidOnly": false,
		"status": "NOT_STARTED",
		"frontendQuestionId": "LCP 01",
		"isFavor": false,
		"solutionNum": 759,
		"title": "Guess Numbers",
		"titleCn": "猜数字",
		"titleSlug": "guess-numbers"
	},
	{
		"__typename": "QuestionLightNode",
		"acRate": 0.6990776926684383,
		"difficulty": "EASY",
		"freqBar": 0,
		"paidOnly": false,
		"status": "NOT_STARTED",
		"frontendQuestionId": "LCP 02",
		"isFavor": false,
		"solutionNum": 307,
		"title": "Deep Dark Fraction",
		"titleCn": "分式化简",
		"titleSlug": "deep-dark-fraction"
	},
	{
		"__typename": "QuestionLightNode",
		"acRate": 0.22920174073250532,
		"difficulty": "MEDIUM",
		"freqBar": 0,
		"paidOnly": false,
		"status": "NOT_STARTED",
		"frontendQuestionId": "LCP 03",
		"isFavor": false,
		"solutionNum": 224,
		"title": "Programmable Robot",
		"titleCn": "机器人大冒险",
		"titleSlug": "programmable-robot"
	},
	{
		"__typename": "QuestionLightNode",
		"acRate": 0.40723235876016706,
		"difficulty": "HARD",
		"freqBar": 0,
		"paidOnly": false,
		"status": "NOT_STARTED",
		"frontendQuestionId": "LCP 04",
		"isFavor": false,
		"solutionNum": 81,
		"title": "Broken Board Dominoes",
		"titleCn": "覆盖",
		"titleSlug": "broken-board-dominoes"
	},
	{
		"__typename": "QuestionLightNode",
		"acRate": 0.2189424846012319,
		"difficulty": "HARD",
		"freqBar": 0,
		"paidOnly": false,
		"status": "NOT_STARTED",
		"frontendQuestionId": "LCP 05",
		"isFavor": false,
		"solutionNum": 64,
		"title": "Coin Bonus",
		"titleCn": "发 LeetCoin",
		"titleSlug": "coin-bonus"
	},
	{
		"__typename": "QuestionLightNode",
		"acRate": 0.8401479446924062,
		"difficulty": "EASY",
		"freqBar": 0,
		"paidOnly": false,
		"status": "NOT_STARTED",
		"frontendQuestionId": "LCP 06",
		"isFavor": false,
		"solutionNum": 810,
		"title": "拿硬币",
		"titleCn": "拿硬币",
		"titleSlug": "na-ying-bi"
	},
	{
		"__typename": "QuestionLightNode",
		"acRate": 0.7624607580842213,
		"difficulty": "EASY",
		"freqBar": 0,
		"paidOnly": false,
		"status": "NOT_STARTED",
		"frontendQuestionId": "LCP 07",
		"isFavor": false,
		"solutionNum": 581,
		"title": "传递信息",
		"titleCn": "传递信息",
		"titleSlug": "chuan-di-xin-xi"
	},
	{
		"__typename": "QuestionLightNode",
		"acRate": 0.31930995581460936,
		"difficulty": "MEDIUM",
		"freqBar": 0,
		"paidOnly": false,
		"status": "NOT_STARTED",
		"frontendQuestionId": "LCP 08",
		"isFavor": false,
		"solutionNum": 124,
		"title": "剧情触发时间",
		"titleCn": "剧情触发时间",
		"titleSlug": "ju-qing-hong-fa-shi-jian"
	},
	{
		"__typename": "QuestionLightNode",
		"acRate": 0.31292581080656806,
		"difficulty": "HARD",
		"freqBar": 0,
		"paidOnly": false,
		"status": "NOT_STARTED",
		"frontendQuestionId": "LCP 09",
		"isFavor": false,
		"solutionNum": 126,
		"title": "最小跳跃次数",
		"titleCn": "最小跳跃次数",
		"titleSlug": "zui-xiao-tiao-yue-ci-shu"
	},
	{
		"__typename": "QuestionLightNode",
		"acRate": 0.6082568807339449,
		"difficulty": "HARD",
		"freqBar": 0,
		"paidOnly": false,
		"status": "NOT_STARTED",
		"frontendQuestionId": "LCP 10",
		"isFavor": false,
		"solutionNum": 46,
		"title": "二叉树任务调度",
		"titleCn": "二叉树任务调度",
		"titleSlug": "er-cha-shu-ren-wu-diao-du"
	},
	{
		"__typename": "QuestionLightNode",
		"acRate": 0.7151249314639304,
		"difficulty": "EASY",
		"freqBar": 0,
		"paidOnly": false,
		"status": "NOT_STARTED",
		"frontendQuestionId": "LCP 11",
		"isFavor": false,
		"solutionNum": 93,
		"title": "期望个数统计",
		"titleCn": "期望个数统计",
		"titleSlug": "qi-wang-ge-shu-tong-ji"
	},
	{
		"__typename": "QuestionLightNode",
		"acRate": 0.4328226411762109,
		"difficulty": "MEDIUM",
		"freqBar": 0,
		"paidOnly": false,
		"status": "NOT_STARTED",
		"frontendQuestionId": "LCP 12",
		"isFavor": false,
		"solutionNum": 143,
		"title": "小张刷题计划",
		"titleCn": "小张刷题计划",
		"titleSlug": "xiao-zhang-shua-ti-ji-hua"
	},
	{
		"__typename": "QuestionLightNode",
		"acRate": 0.6046047860768673,
		"difficulty": "HARD",
		"freqBar": 0,
		"paidOnly": false,
		"status": "NOT_STARTED",
		"frontendQuestionId": "LCP 13",
		"isFavor": false,
		"solutionNum": 96,
		"title": "寻宝",
		"titleCn": "寻宝",
		"titleSlug": "xun-bao"
	},
	{
		"__typename": "QuestionLightNode",
		"acRate": 0.2324331410592554,
		"difficulty": "HARD",
		"freqBar": 0,
		"paidOnly": false,
		"status": "NOT_STARTED",
		"frontendQuestionId": "LCP 14",
		"isFavor": false,
		"solutionNum": 54,
		"title": "切分数组",
		"titleCn": "切分数组",
		"titleSlug": "qie-fen-shu-zu"
	},
	{
		"__typename": "QuestionLightNode",
		"acRate": 0.6073194856577646,
		"difficulty": "HARD",
		"freqBar": 0,
		"paidOnly": false,
		"status": "NOT_STARTED",
		"frontendQuestionId": "LCP 15",
		"isFavor": false,
		"solutionNum": 28,
		"title": "游乐园的迷宫",
		"titleCn": "游乐园的迷宫",
		"titleSlug": "you-le-yuan-de-mi-gong"
	},
	{
		"__typename": "QuestionLightNode",
		"acRate": 0.3421760861207228,
		"difficulty": "HARD",
		"freqBar": 0,
		"paidOnly": false,
		"status": "NOT_STARTED",
		"frontendQuestionId": "LCP 16",
		"isFavor": false,
		"solutionNum": 20,
		"title": "游乐园的游览计划",
		"titleCn": "游乐园的游览计划",
		"titleSlug": "you-le-yuan-de-you-lan-ji-hua"
	},
	{
		"__typename": "QuestionLightNode",
		"acRate": 0.8015680418144484,
		"difficulty": "EASY",
		"freqBar": 0,
		"paidOnly": false,
		"status": "NOT_STARTED",
		"frontendQuestionId": "LCP 17",
		"isFavor": false,
		"solutionNum": 334,
		"title": "速算机器人",
		"titleCn": "速算机器人",
		"titleSlug": "nGK0Fy"
	},
	{
		"__typename": "QuestionLightNode",
		"acRate": 0.2998472764296623,
		"difficulty": "EASY",
		"freqBar": 0,
		"paidOnly": false,
		"status": "NOT_STARTED",
		"frontendQuestionId": "LCP 18",
		"isFavor": false,
		"solutionNum": 328,
		"title": "早餐组合",
		"titleCn": "早餐组合",
		"titleSlug": "2vYnGI"
	},
	{
		"__typename": "QuestionLightNode",
		"acRate": 0.5180737476696607,
		"difficulty": "MEDIUM",
		"freqBar": 0,
		"paidOnly": false,
		"status": "NOT_STARTED",
		"frontendQuestionId": "LCP 19",
		"isFavor": false,
		"solutionNum": 229,
		"title": "秋叶收藏集",
		"titleCn": "秋叶收藏集",
		"titleSlug": "UlBDOe"
	},
	{
		"__typename": "QuestionLightNode",
		"acRate": 0.3496804874424134,
		"difficulty": "HARD",
		"freqBar": 0,
		"paidOnly": false,
		"status": "NOT_STARTED",
		"frontendQuestionId": "LCP 20",
		"isFavor": false,
		"solutionNum": 35,
		"title": "快速公交",
		"titleCn": "快速公交",
		"titleSlug": "meChtZ"
	},
	{
		"__typename": "QuestionLightNode",
		"acRate": 0.3757257395631739,
		"difficulty": "HARD",
		"freqBar": 0,
		"paidOnly": false,
		"status": "NOT_STARTED",
		"frontendQuestionId": "LCP 21",
		"isFavor": false,
		"solutionNum": 33,
		"title": "追逐游戏",
		"titleCn": "追逐游戏",
		"titleSlug": "Za25hA"
	},
	{
		"__typename": "QuestionLightNode",
		"acRate": 0.34505250799034637,
		"difficulty": "EASY",
		"freqBar": 0,
		"paidOnly": false,
		"status": "NOT_STARTED",
		"frontendQuestionId": "LCP 22",
		"isFavor": false,
		"solutionNum": 211,
		"title": "黑白方格画",
		"titleCn": "黑白方格画",
		"titleSlug": "ccw6C7"
	},
	{
		"__typename": "QuestionLightNode",
		"acRate": 0.3625156707062265,
		"difficulty": "MEDIUM",
		"freqBar": 0,
		"paidOnly": false,
		"status": "NOT_STARTED",
		"frontendQuestionId": "LCP 23",
		"isFavor": false,
		"solutionNum": 63,
		"title": "魔术排列",
		"titleCn": "魔术排列",
		"titleSlug": "er94lq"
	},
	{
		"__typename": "QuestionLightNode",
		"acRate": 0.30973871733966746,
		"difficulty": "HARD",
		"freqBar": 0,
		"paidOnly": false,
		"status": "NOT_STARTED",
		"frontendQuestionId": "LCP 24",
		"isFavor": false,
		"solutionNum": 30,
		"title": "数字游戏",
		"titleCn": "数字游戏",
		"titleSlug": "5TxKeK"
	},
	{
		"__typename": "QuestionLightNode",
		"acRate": 0.3662578007316548,
		"difficulty": "HARD",
		"freqBar": 0,
		"paidOnly": false,
		"status": "NOT_STARTED",
		"frontendQuestionId": "LCP 25",
		"isFavor": false,
		"solutionNum": 34,
		"title": "古董键盘",
		"titleCn": "古董键盘",
		"titleSlug": "Uh984O"
	},
	{
		"__typename": "QuestionLightNode",
		"acRate": 0.37144108628996936,
		"difficulty": "HARD",
		"freqBar": 0,
		"paidOnly": false,
		"status": "NOT_STARTED",
		"frontendQuestionId": "LCP 26",
		"isFavor": false,
		"solutionNum": 24,
		"title": "导航装置",
		"titleCn": "导航装置",
		"titleSlug": "hSRGyL"
	},
	{
		"__typename": "QuestionLightNode",
		"acRate": 0.3375137513751375,
		"difficulty": "HARD",
		"freqBar": 0,
		"paidOnly": false,
		"status": "NOT_STARTED",
		"frontendQuestionId": "LCP 27",
		"isFavor": false,
		"solutionNum": 31,
		"title": "黑盒光线反射",
		"titleCn": "黑盒光线反射",
		"titleSlug": "IQvJ9i"
	},
	{
		"__typename": "QuestionLightNode",
		"acRate": 0.31372258172176587,
		"difficulty": "EASY",
		"freqBar": 0,
		"paidOnly": false,
		"status": "NOT_STARTED",
		"frontendQuestionId": "LCP 28",
		"isFavor": false,
		"solutionNum": 274,
		"title": "采购方案",
		"titleCn": "采购方案",
		"titleSlug": "4xy4Wx"
	},
	{
		"__typename": "QuestionLightNode",
		"acRate": 0.21130555479955365,
		"difficulty": "MEDIUM",
		"freqBar": 0,
		"paidOnly": false,
		"status": "NOT_STARTED",
		"frontendQuestionId": "LCP 29",
		"isFavor": false,
		"solutionNum": 165,
		"title": "乐团站位",
		"titleCn": "乐团站位",
		"titleSlug": "SNJvJP"
	},
	{
		"__typename": "QuestionLightNode",
		"acRate": 0.37558461804954096,
		"difficulty": "MEDIUM",
		"freqBar": 0,
		"paidOnly": false,
		"status": "NOT_STARTED",
		"frontendQuestionId": "LCP 30",
		"isFavor": false,
		"solutionNum": 138,
		"title": "魔塔游戏",
		"titleCn": "魔塔游戏",
		"titleSlug": "p0NxJO"
	},
	{
		"__typename": "QuestionLightNode",
		"acRate": 0.28771384136858474,
		"difficulty": "HARD",
		"freqBar": 0,
		"paidOnly": false,
		"status": "NOT_STARTED",
		"frontendQuestionId": "LCP 31",
		"isFavor": false,
		"solutionNum": 41,
		"title": "变换的迷宫",
		"titleCn": "变换的迷宫",
		"titleSlug": "Db3wC1"
	},
	{
		"__typename": "QuestionLightNode",
		"acRate": 0.4412864622288706,
		"difficulty": "HARD",
		"freqBar": 0,
		"paidOnly": false,
		"status": "NOT_STARTED",
		"frontendQuestionId": "LCP 32",
		"isFavor": false,
		"solutionNum": 29,
		"title": "批量处理任务",
		"titleCn": "批量处理任务",
		"titleSlug": "t3fKg1"
	},
	{
		"__typename": "QuestionLightNode",
		"acRate": 0.2588307533206218,
		"difficulty": "EASY",
		"freqBar": 0,
		"paidOnly": false,
		"status": "NOT_STARTED",
		"frontendQuestionId": "LCP 33",
		"isFavor": false,
		"solutionNum": 130,
		"title": "蓄水",
		"titleCn": "蓄水",
		"titleSlug": "o8SXZn"
	},
	{
		"__typename": "QuestionLightNode",
		"acRate": 0.5495317890586496,
		"difficulty": "MEDIUM",
		"freqBar": 0,
		"paidOnly": false,
		"status": "NOT_STARTED",
		"frontendQuestionId": "LCP 34",
		"isFavor": false,
		"solutionNum": 87,
		"title": "二叉树染色",
		"titleCn": "二叉树染色",
		"titleSlug": "er-cha-shu-ran-se-UGC"
	},
	{
		"__typename": "QuestionLightNode",
		"acRate": 0.4799453053783045,
		"difficulty": "HARD",
		"freqBar": 0,
		"paidOnly": false,
		"status": "NOT_STARTED",
		"frontendQuestionId": "LCP 35",
		"isFavor": false,
		"solutionNum": 34,
		"title": "电动车游城市",
		"titleCn": "电动车游城市",
		"titleSlug": "DFPeFJ"
	},
	{
		"__typename": "QuestionLightNode",
		"acRate": 0.33379888268156427,
		"difficulty": "HARD",
		"freqBar": 0,
		"paidOnly": false,
		"status": "NOT_STARTED",
		"frontendQuestionId": "LCP 36",
		"isFavor": false,
		"solutionNum": 24,
		"title": "最多牌组数",
		"titleCn": "最多牌组数",
		"titleSlug": "Up5XYM"
	},
	{
		"__typename": "QuestionLightNode",
		"acRate": 0.24643799472295513,
		"difficulty": "HARD",
		"freqBar": 0,
		"paidOnly": false,
		"status": "NOT_STARTED",
		"frontendQuestionId": "LCP 37",
		"isFavor": false,
		"solutionNum": 26,
		"title": "最小矩形面积",
		"titleCn": "最小矩形面积",
		"titleSlug": "zui-xiao-ju-xing-mian-ji"
	},
	{
		"__typename": "QuestionLightNode",
		"acRate": 0.5589419206440484,
		"difficulty": "HARD",
		"freqBar": 0,
		"paidOnly": false,
		"status": "NOT_STARTED",
		"frontendQuestionId": "LCP 38",
		"isFavor": false,
		"solutionNum": 19,
		"title": "守卫城堡",
		"titleCn": "守卫城堡",
		"titleSlug": "7rLGCR"
	},
	{
		"__typename": "QuestionLightNode",
		"acRate": 0.5489403926571692,
		"difficulty": "EASY",
		"freqBar": 0,
		"paidOnly": false,
		"status": "NOT_STARTED",
		"frontendQuestionId": "LCP 39",
		"isFavor": false,
		"solutionNum": 83,
		"title": "无人机方阵",
		"titleCn": "无人机方阵",
		"titleSlug": "0jQkd0"
	},
	{
		"__typename": "QuestionLightNode",
		"acRate": 0.3065959562479284,
		"difficulty": "EASY",
		"freqBar": 0,
		"paidOnly": false,
		"status": "NOT_STARTED",
		"frontendQuestionId": "LCP 40",
		"isFavor": false,
		"solutionNum": 151,
		"title": "心算挑战",
		"titleCn": "心算挑战",
		"titleSlug": "uOAnQW"
	},
	{
		"__typename": "QuestionLightNode",
		"acRate": 0.5063469675599436,
		"difficulty": "MEDIUM",
		"freqBar": 0,
		"paidOnly": false,
		"status": "NOT_STARTED",
		"frontendQuestionId": "LCP 41",
		"isFavor": false,
		"solutionNum": 60,
		"title": "黑白翻转棋",
		"titleCn": "黑白翻转棋",
		"titleSlug": "fHi6rV"
	},
	{
		"__typename": "QuestionLightNode",
		"acRate": 0.28376600071778924,
		"difficulty": "HARD",
		"freqBar": 0,
		"paidOnly": false,
		"status": "NOT_STARTED",
		"frontendQuestionId": "LCP 42",
		"isFavor": false,
		"solutionNum": 45,
		"title": "玩具套圈",
		"titleCn": "玩具套圈",
		"titleSlug": "vFjcfV"
	},
	{
		"__typename": "QuestionLightNode",
		"acRate": 0.5183009489380931,
		"difficulty": "HARD",
		"freqBar": 0,
		"paidOnly": false,
		"status": "NOT_STARTED",
		"frontendQuestionId": "LCP 43",
		"isFavor": false,
		"solutionNum": 29,
		"title": "十字路口的交通",
		"titleCn": "十字路口的交通",
		"titleSlug": "Y1VbOX"
	},
	{
		"__typename": "QuestionLightNode",
		"acRate": 0.8012919533773346,
		"difficulty": "EASY",
		"freqBar": 0,
		"paidOnly": false,
		"status": "NOT_STARTED",
		"frontendQuestionId": "LCP 44",
		"isFavor": false,
		"solutionNum": 160,
		"title": "开幕式焰火",
		"titleCn": "开幕式焰火",
		"titleSlug": "sZ59z6"
	},
	{
		"__typename": "QuestionLightNode",
		"acRate": 0.2768389662027833,
		"difficulty": "MEDIUM",
		"freqBar": 0,
		"paidOnly": false,
		"status": "NOT_STARTED",
		"frontendQuestionId": "LCP 45",
		"isFavor": false,
		"solutionNum": 53,
		"title": "自行车炫技赛场",
		"titleCn": "自行车炫技赛场",
		"titleSlug": "kplEvH"
	},
	{
		"__typename": "QuestionLightNode",
		"acRate": 0.47440178074568723,
		"difficulty": "MEDIUM",
		"freqBar": 0,
		"paidOnly": false,
		"status": "NOT_STARTED",
		"frontendQuestionId": "LCP 46",
		"isFavor": false,
		"solutionNum": 40,
		"title": "志愿者调配",
		"titleCn": "志愿者调配",
		"titleSlug": "05ZEDJ"
	},
	{
		"__typename": "QuestionLightNode",
		"acRate": 0.437289088863892,
		"difficulty": "HARD",
		"freqBar": 0,
		"paidOnly": false,
		"status": "NOT_STARTED",
		"frontendQuestionId": "LCP 47",
		"isFavor": false,
		"solutionNum": 29,
		"title": "入场安检",
		"titleCn": "入场安检",
		"titleSlug": "oPs9Bm"
	},
	{
		"__typename": "QuestionLightNode",
		"acRate": 0.2685003274394237,
		"difficulty": "HARD",
		"freqBar": 0,
		"paidOnly": false,
		"status": "NOT_STARTED",
		"frontendQuestionId": "LCP 48",
		"isFavor": false,
		"solutionNum": 16,
		"title": "无限棋局",
		"titleCn": "无限棋局",
		"titleSlug": "fsa7oZ"
	},
	{
		"__typename": "QuestionLightNode",
		"acRate": 0.3567522086663862,
		"difficulty": "HARD",
		"freqBar": 0,
		"paidOnly": false,
		"status": "NOT_STARTED",
		"frontendQuestionId": "LCP 49",
		"isFavor": false,
		"solutionNum": 18,
		"title": "环形闯关游戏",
		"titleCn": "环形闯关游戏",
		"titleSlug": "K8GULz"
	}
]